purly/__init__.py
purly/html.py
purly/layout.py
purly/state.py
purly/utils.py
purly/model/__init__.py
purly/model/client.py
purly/model/server.py
purly/model/utils.py
purly/static/board/asset-manifest.json
purly/static/board/index.html
purly/static/board/manifest.json
purly/static/board/service-worker.js
purly/static/board/public/favicon.ico
purly/static/board/static/js/main.5d96a6ab.js
purly/static/board/static/js/main.5d96a6ab.js.map
purly/static/widget/asset-manifest.json
purly/static/widget/index.html
purly/static/widget/service-worker.js
purly/static/widget/static/js/main.addbb624.js
purly/static/widget/static/js/main.addbb624.js.map
purly-0.2.0.dist-info/METADATA
purly-0.2.0.dist-info/RECORD
purly-0.2.0.dist-info/WHEEL
purly-0.2.0.dist-info/top_level.txt
