Metadata-Version: 2.1
Name: purly
Version: 0.2.0
Summary: Control the web with Python
Home-page: https://github.com/rmorshea/purly
Author: Ryan Morshead
Author-email: ryan.morshead@gmail.com
License: MIT
Keywords: interactive,widgets,DOM,synchronization,React
Platform: Linux
Platform: Mac OS X
Platform: Windows
Classifier: Intended Audience :: Developers
Classifier: Programming Language :: Python :: 3.6
Requires-Dist: sanic
Requires-Dist: sanic-cors
Requires-Dist: asyncio
Requires-Dist: websocket-client
Requires-Dist: websockets (==5.0)
Requires-Dist: spectate (>=0.2.1)
